smilelog/Controller.py
smilelog/FCMLib.py
smilelog/Logger.py
smilelog/RedisLib.py
smilelog/SDK.py
smilelog/__init__.py
smilelog/cli.py
SmileLog-4.1.4.dist-info/LICENSE.txt
SmileLog-4.1.4.dist-info/METADATA
SmileLog-4.1.4.dist-info/WHEEL
SmileLog-4.1.4.dist-info/top_level.txt
SmileLog-4.1.4.dist-info/RECORD
