Metadata-Version: 2.1
Name: SmileLog
Version: 4.1.4
Summary: Log library
Home-page: https://github.com/sitthykun/smilelog
Author: Sitthykun LY
Author-email: ly.sitthykun@gmail.com
License: MIT License
Keywords: smilelog,log,logger,console,consoler,trace,tracking,redis
Platform: All
Classifier: Programming Language :: Python :: 3.8
Classifier: Programming Language :: Python :: 3.9
Classifier: Programming Language :: Python :: 3.10
Classifier: Programming Language :: Python :: 3.11
Classifier: Programming Language :: Python :: 3.12
Classifier: License :: OSI Approved :: MIT License
Classifier: Operating System :: OS Independent
Requires-Python: >=3.8
License-File: LICENSE.txt
Requires-Dist: redis >=5.0.0
